litedis/__init__.py
litedis/commandline.py
litedis/litedis.py
litedis/typing.py
litedis/utils.py
litedis/client/__init__.py
litedis/client/commands.py
litedis/core/__init__.py
litedis/core/dbcommand.py
litedis/core/dbmanager.py
litedis/core/command/__init__.py
litedis/core/command/base.py
litedis/core/command/basiccmds.py
litedis/core/command/factory.py
litedis/core/command/hashcmds.py
litedis/core/command/listcmds.py
litedis/core/command/setcmds.py
litedis/core/command/sortedset.py
litedis/core/command/zsetcmds.py
litedis/core/persistence/__init__.py
litedis/core/persistence/aof.py
litedis/core/persistence/ldb.py
litedis-3.0.8.dist-info/METADATA
litedis-3.0.8.dist-info/WHEEL
litedis-3.0.8.dist-info/top_level.txt
litedis-3.0.8.dist-info/RECORD
