Metadata-Version: 2.1
Name: litedis
Version: 3.0.8
Summary: Litedis 是一个类似 Redis 的轻量级的、本地的、开箱即用的 NoSQL 数据库。Litedis is a lightweight, local, out-of-the-box NoSQL database similar to Redis.
Home-page: https://github.com/linsuiyuan/litedis
Author: Linsuiyuan
Author-email: linsuiyuan@icloud.com
Classifier: Programming Language :: Python :: 3
Classifier: License :: OSI Approved :: MIT License
Classifier: Operating System :: OS Independent
Requires-Python: >=3.8
Requires-Dist: sortedcontainers
